{
  "results": {
    "truthfulqa_pt_mc": {
      "mc1": 0.22842639593908629,
      "mc1_stderr": 0.014964922033138024,
      "mc2": 0.3823261607330551,
      "mc2_stderr": 0.01463319398314419
    }
  },
  "versions": {
    "truthfulqa_pt_mc": 1
  },
  "config": {
    "model": "hf-auto",
    "model_args": "pretrained=/sensei-fs/users/daclai/uoChatGPT/llama-7B",
    "batch_size": "1",
    "device": "cuda",
    "no_cache": false,
    "limit": null,
    "bootstrap_iters": 100000,
    "description_dict": {}
  }
}